bcmd/__init__.py
bcmd/common/__init__.py
bcmd/common/func.py
bcmd/common/secret.py
bcmd/resources/project/main.py
bcmd/tasks/__init__.py
bcmd/tasks/amazon.py
bcmd/tasks/bin.py
bcmd/tasks/code.py
bcmd/tasks/crypto.py
bcmd/tasks/docs.py
bcmd/tasks/download.py
bcmd/tasks/image.py
bcmd/tasks/json.py
bcmd/tasks/lib.py
bcmd/tasks/math.py
bcmd/tasks/mirror.py
bcmd/tasks/pdf.py
bcmd/tasks/project.py
bcmd/tasks/proxy.py
bcmd/tasks/time.py
bcmd/tasks/upgrade.py
bcmd/tasks/wasabi.py
bcmd/tasks/watermark.py
bcmd/utils/__init__.py
test/__init__.py
test/conftest.py
test/test_pdf.py
test/test_proxy.py
test/test_wasabi.py
bcmd-0.6.43.dist-info/METADATA
bcmd-0.6.43.dist-info/WHEEL
bcmd-0.6.43.dist-info/entry_points.txt
bcmd-0.6.43.dist-info/top_level.txt
bcmd-0.6.43.dist-info/RECORD
