Metadata-Version: 2.4
Name: bcmd
Version: 0.6.43
Summary: Commands for Beni
Author-email: Beni Mang <benimang@126.com>
Maintainer-email: Beni Mang <benimang@126.com>
Keywords: benimang,beni,bcmd
Requires-Python: >=3.10
Requires-Dist: aioconsole>=0.8.1
Requires-Dist: async-lru>=2.0.5
Requires-Dist: benimang>=0.8.16
Requires-Dist: cryptography>=45.0.4
Requires-Dist: nest-asyncio>=1.6.0
Requires-Dist: paramiko>=3.5.1
Requires-Dist: pillow>=11.2.1
Requires-Dist: playwright>=1.57.0
Requires-Dist: prettytable>=3.16.0
Requires-Dist: pymupdf>=1.26.1
Requires-Dist: qiniu>=7.16.0
Requires-Dist: typer>=0.16.0
Provides-Extra: full
Requires-Dist: img2pdf>=0.6.1; extra == "full"
Requires-Dist: pytest>=8.4.0; extra == "full"
Requires-Dist: pytest-asyncio>=1.0.0; extra == "full"
Requires-Dist: pytest-order>=1.3.0; extra == "full"
